Workbook
Name ClientList: 'Setup - Clients'!$A$5:$A$504
Name GradeList: 'Setup - Mix Design'!$A$5:$A$504
Name VehicleList: 'Setup - Vehicles'!$A$5:$A$504
Name VehStatusList: 'Lists'!$A$2:$A$4
Name DriverList: 'Setup - Drivers'!$A$5:$A$504
Name MaterialList: 'Setup - Materials'!$A$5:$A$504
Name DispStatusList: 'Lists'!$B$2:$B$5
Name ChallanList: 'Dispatch (Challan)'!$B$5:$B$6004
Name PayModeList: 'Lists'!$C$2:$C$6

Sheet Instructions
A1: CONCRETE KING • RMC Plant Daily Workbook
A2: One connected, automated workbook for ready-mix concrete plant operations
B5: HOW IT WORKS
B6: 1. Fill the Setup tabs once | C6: Enter Clients, Mix Designs (grades), Vehicles, Drivers and Materials. Everything else pulls from these via dropdowns.
B7: 2. Record daily work | C7: Use Orders, Dispatch, Batch Production, Material Receipt, Fuel Log, Payments and Cube Tests every day. Pick values from dropdowns - no retyping.
B8: 3. Numbers self-calculate | C8: Rates, amounts, mix consumption, stock, outstanding and test results auto-fill. Less entry, more connectivity.
B9: 4. Read Dashboard & Monthly Summary | C9: Live KPIs, charts and month-wise totals across the whole plant.
B11: CAPACITY
B12: 6,000 rows per daily sheet | C12: Each transaction sheet holds 6,000 entries - well over 700/month for a full year. To add even more, click the last filled cell and drag the small handle down.
B14: COLOUR GUIDE
B15: Gold cells = you type here | C15: Your entry cells (clients, quantities, dates...).
B16: Blue cells = auto-calculated | C16: Do NOT type in blue cells - they fill automatically.
B17: Red highlight = attention | C17: Low stock (below reorder level) and Failed cube tests turn red automatically.
B19: WHAT'S INSIDE
B20: Dashboard | C20: Live KPIs + charts: production, dispatch, sales, collection, outstanding, stock levels.
B21: Monthly Summary | C21: Auto month-wise production, dispatch, sales, collection & purchases for the year you choose.
B22: Setup - Clients / Mix Design / Vehicles / Drivers / Materials | C22: Master data. Mix Design also sets material per m3 + selling rate; Materials sets opening stock, rate & reorder level.
B23: Orders | C23: Order book - rate, value, delivered qty, balance & status auto-calculate.
B24: Dispatch (Challan) | C24: Delivery challans - driver, rate & amount auto-fill; delivered qty rolls up to Orders.
B25: Batch Production | C25: Enter grade + m3; cement/sand/aggregate/water/admixture consumed auto-compute.
B26: Material Receipt | C26: Raw material purchases - feeds stock.
B27: Fuel Log | C27: Diesel issued per vehicle.
B28: Payments | C28: Customer collections - drives outstanding on the Dashboard.
B29: Cube Test Register | C29: 7 / 28-day cube strength with automatic Pass/Fail vs grade requirement.
B30: Stock Register | C30: Opening + Received - Consumed = Closing, per material, with low-stock alerts.

Sheet Dashboard
A1: Dashboard - Plant Overview
A2: Live totals across the whole workbook.
B4: TOTAL PRODUCTION (m3) | E4: TOTAL DISPATCHED (m3)
B5: =SUM('Batch Production'!$D$5:$D$6004) | E5: =SUM('Dispatch (Challan)'!$F$5:$F$6004)
B7: DISPATCHED VALUE (₹) | E7: COLLECTION (₹)
B8: =SUM('Dispatch (Challan)'!$J$5:$J$6004) | E8: =SUM('Payments'!$D$5:$D$6004)
B10: OUTSTANDING (₹) | E10: MATERIAL PURCHASE (₹)
B11: =SUM('Dispatch (Challan)'!$J$5:$J$6004)-SUM('Payments'!$D$5:$D$6004) | E11: =SUM('Material Receipt'!$F$5:$F$6004)
B14: PRODUCTION BY GRADE
B15: Grade | C15: Produced (m3)
B16: M15 | C16: =SUMIF('Batch Production'!$C$5:$C$6004,B16,'Batch Production'!$D$5:$D$6004)
B17: M20 | C17: =SUMIF('Batch Production'!$C$5:$C$6004,B17,'Batch Production'!$D$5:$D$6004)
B18: M25 | C18: =SUMIF('Batch Production'!$C$5:$C$6004,B18,'Batch Production'!$D$5:$D$6004)
B19: M30 | C19: =SUMIF('Batch Production'!$C$5:$C$6004,B19,'Batch Production'!$D$5:$D$6004)
B20: M35 | C20: =SUMIF('Batch Production'!$C$5:$C$6004,B20,'Batch Production'!$D$5:$D$6004)
B21: M40 | C21: =SUMIF('Batch Production'!$C$5:$C$6004,B21,'Batch Production'!$D$5:$D$6004)

Sheet Monthly Summary
A1: Monthly Summary - Year View
A2: Set the year; every month total fills automatically.
B4: Year: | C4: 2026
B6: Month | C6: Production (m3) | D6: Dispatched (m3) | E6: Sales Value (₹) | F6: Collection (₹) | G6: Purchases (₹)
B7: Jan | C7: =SUMIFS('Batch Production'!$D$5:$D$6004,'Batch Production'!$A$5:$A$6004,">="&DATE($C$4,1,1),'Batch Production'!$A$5:$A$6004,"<"&DATE($C$4,1+1,1)) | D7: =SUMIFS('Dispatch (Challan)'!$F$5:$F$6004,'Dispatch (Challan)'!$A$5:$A$6004,">="&DATE($C$4,1,1),'Dispatch (Challan)'!$A$5:$A$6004,"<"&DATE($C$4,1+1,1)) | E7: =SUMIFS('Dispatch (Challan)'!$J$5:$J$6004,'Dispatch (Challan)'!$A$5:$A$6004,">="&DATE($C$4,1,1),'Dispatch (Challan)'!$A$5:$A$6004,"<"&DATE($C$4,1+1,1)) | F7: =SUMIFS('Payments'!$D$5:$D$6004,'Payments'!$A$5:$A$6004,">="&DATE($C$4,1,1),'Payments'!$A$5:$A$6004,"<"&DATE($C$4,1+1,1)) | G7: =SUMIFS('Material Receipt'!$F$5:$F$6004,'Material Receipt'!$A$5:$A$6004,">="&DATE($C$4,1,1),'Material Receipt'!$A$5:$A$6004,"<"&DATE($C$4,1+1,1))
B8: Feb | C8: =SUMIFS('Batch Production'!$D$5:$D$6004,'Batch Production'!$A$5:$A$6004,">="&DATE($C$4,2,1),'Batch Production'!$A$5:$A$6004,"<"&DATE($C$4,2+1,1)) | D8: =SUMIFS('Dispatch (Challan)'!$F$5:$F$6004,'Dispatch (Challan)'!$A$5:$A$6004,">="&DATE($C$4,2,1),'Dispatch (Challan)'!$A$5:$A$6004,"<"&DATE($C$4,2+1,1)) | E8: =SUMIFS('Dispatch (Challan)'!$J$5:$J$6004,'Dispatch (Challan)'!$A$5:$A$6004,">="&DATE($C$4,2,1),'Dispatch (Challan)'!$A$5:$A$6004,"<"&DATE($C$4,2+1,1)) | F8: =SUMIFS('Payments'!$D$5:$D$6004,'Payments'!$A$5:$A$6004,">="&DATE($C$4,2,1),'Payments'!$A$5:$A$6004,"<"&DATE($C$4,2+1,1)) | G8: =SUMIFS('Material Receipt'!$F$5:$F$6004,'Material Receipt'!$A$5:$A$6004,">="&DATE($C$4,2,1),'Material Receipt'!$A$5:$A$6004,"<"&DATE($C$4,2+1,1))
B9: Mar | C9: =SUMIFS('Batch Production'!$D$5:$D$6004,'Batch Production'!$A$5:$A$6004,">="&DATE($C$4,3,1),'Batch Production'!$A$5:$A$6004,"<"&DATE($C$4,3+1,1)) | D9: =SUMIFS('Dispatch (Challan)'!$F$5:$F$6004,'Dispatch (Challan)'!$A$5:$A$6004,">="&DATE($C$4,3,1),'Dispatch (Challan)'!$A$5:$A$6004,"<"&DATE($C$4,3+1,1)) | E9: =SUMIFS('Dispatch (Challan)'!$J$5:$J$6004,'Dispatch (Challan)'!$A$5:$A$6004,">="&DATE($C$4,3,1),'Dispatch (Challan)'!$A$5:$A$6004,"<"&DATE($C$4,3+1,1)) | F9: =SUMIFS('Payments'!$D$5:$D$6004,'Payments'!$A$5:$A$6004,">="&DATE($C$4,3,1),'Payments'!$A$5:$A$6004,"<"&DATE($C$4,3+1,1)) | G9: =SUMIFS('Material Receipt'!$F$5:$F$6004,'Material Receipt'!$A$5:$A$6004,">="&DATE($C$4,3,1),'Material Receipt'!$A$5:$A$6004,"<"&DATE($C$4,3+1,1))
B10: Apr | C10: =SUMIFS('Batch Production'!$D$5:$D$6004,'Batch Production'!$A$5:$A$6004,">="&DATE($C$4,4,1),'Batch Production'!$A$5:$A$6004,"<"&DATE($C$4,4+1,1)) | D10: =SUMIFS('Dispatch (Challan)'!$F$5:$F$6004,'Dispatch (Challan)'!$A$5:$A$6004,">="&DATE($C$4,4,1),'Dispatch (Challan)'!$A$5:$A$6004,"<"&DATE($C$4,4+1,1)) | E10: =SUMIFS('Dispatch (Challan)'!$J$5:$J$6004,'Dispatch (Challan)'!$A$5:$A$6004,">="&DATE($C$4,4,1),'Dispatch (Challan)'!$A$5:$A$6004,"<"&DATE($C$4,4+1,1)) | F10: =SUMIFS('Payments'!$D$5:$D$6004,'Payments'!$A$5:$A$6004,">="&DATE($C$4,4,1),'Payments'!$A$5:$A$6004,"<"&DATE($C$4,4+1,1)) | G10: =SUMIFS('Material Receipt'!$F$5:$F$6004,'Material Receipt'!$A$5:$A$6004,">="&DATE($C$4,4,1),'Material Receipt'!$A$5:$A$6004,"<"&DATE($C$4,4+1,1))
B11: May | C11: =SUMIFS('Batch Production'!$D$5:$D$6004,'Batch Production'!$A$5:$A$6004,">="&DATE($C$4,5,1),'Batch Production'!$A$5:$A$6004,"<"&DATE($C$4,5+1,1)) | D11: =SUMIFS('Dispatch (Challan)'!$F$5:$F$6004,'Dispatch (Challan)'!$A$5:$A$6004,">="&DATE($C$4,5,1),'Dispatch (Challan)'!$A$5:$A$6004,"<"&DATE($C$4,5+1,1)) | E11: =SUMIFS('Dispatch (Challan)'!$J$5:$J$6004,'Dispatch (Challan)'!$A$5:$A$6004,">="&DATE($C$4,5,1),'Dispatch (Challan)'!$A$5:$A$6004,"<"&DATE($C$4,5+1,1)) | F11: =SUMIFS('Payments'!$D$5:$D$6004,'Payments'!$A$5:$A$6004,">="&DATE($C$4,5,1),'Payments'!$A$5:$A$6004,"<"&DATE($C$4,5+1,1)) | G11: =SUMIFS('Material Receipt'!$F$5:$F$6004,'Material Receipt'!$A$5:$A$6004,">="&DATE($C$4,5,1),'Material Receipt'!$A$5:$A$6004,"<"&DATE($C$4,5+1,1))
B12: Jun | C12: =SUMIFS('Batch Production'!$D$5:$D$6004,'Batch Production'!$A$5:$A$6004,">="&DATE($C$4,6,1),'Batch Production'!$A$5:$A$6004,"<"&DATE($C$4,6+1,1)) | D12: =SUMIFS('Dispatch (Challan)'!$F$5:$F$6004,'Dispatch (Challan)'!$A$5:$A$6004,">="&DATE($C$4,6,1),'Dispatch (Challan)'!$A$5:$A$6004,"<"&DATE($C$4,6+1,1)) | E12: =SUMIFS('Dispatch (Challan)'!$J$5:$J$6004,'Dispatch (Challan)'!$A$5:$A$6004,">="&DATE($C$4,6,1),'Dispatch (Challan)'!$A$5:$A$6004,"<"&DATE($C$4,6+1,1)) | F12: =SUMIFS('Payments'!$D$5:$D$6004,'Payments'!$A$5:$A$6004,">="&DATE($C$4,6,1),'Payments'!$A$5:$A$6004,"<"&DATE($C$4,6+1,1)) | G12: =SUMIFS('Material Receipt'!$F$5:$F$6004,'Material Receipt'!$A$5:$A$6004,">="&DATE($C$4,6,1),'Material Receipt'!$A$5:$A$6004,"<"&DATE($C$4,6+1,1))
B13: Jul | C13: =SUMIFS('Batch Production'!$D$5:$D$6004,'Batch Production'!$A$5:$A$6004,">="&DATE($C$4,7,1),'Batch Production'!$A$5:$A$6004,"<"&DATE($C$4,7+1,1)) | D13: =SUMIFS('Dispatch (Challan)'!$F$5:$F$6004,'Dispatch (Challan)'!$A$5:$A$6004,">="&DATE($C$4,7,1),'Dispatch (Challan)'!$A$5:$A$6004,"<"&DATE($C$4,7+1,1)) | E13: =SUMIFS('Dispatch (Challan)'!$J$5:$J$6004,'Dispatch (Challan)'!$A$5:$A$6004,">="&DATE($C$4,7,1),'Dispatch (Challan)'!$A$5:$A$6004,"<"&DATE($C$4,7+1,1)) | F13: =SUMIFS('Payments'!$D$5:$D$6004,'Payments'!$A$5:$A$6004,">="&DATE($C$4,7,1),'Payments'!$A$5:$A$6004,"<"&DATE($C$4,7+1,1)) | G13: =SUMIFS('Material Receipt'!$F$5:$F$6004,'Material Receipt'!$A$5:$A$6004,">="&DATE($C$4,7,1),'Material Receipt'!$A$5:$A$6004,"<"&DATE($C$4,7+1,1))
B14: Aug | C14: =SUMIFS('Batch Production'!$D$5:$D$6004,'Batch Production'!$A$5:$A$6004,">="&DATE($C$4,8,1),'Batch Production'!$A$5:$A$6004,"<"&DATE($C$4,8+1,1)) | D14: =SUMIFS('Dispatch (Challan)'!$F$5:$F$6004,'Dispatch (Challan)'!$A$5:$A$6004,">="&DATE($C$4,8,1),'Dispatch (Challan)'!$A$5:$A$6004,"<"&DATE($C$4,8+1,1)) | E14: =SUMIFS('Dispatch (Challan)'!$J$5:$J$6004,'Dispatch (Challan)'!$A$5:$A$6004,">="&DATE($C$4,8,1),'Dispatch (Challan)'!$A$5:$A$6004,"<"&DATE($C$4,8+1,1)) | F14: =SUMIFS('Payments'!$D$5:$D$6004,'Payments'!$A$5:$A$6004,">="&DATE($C$4,8,1),'Payments'!$A$5:$A$6004,"<"&DATE($C$4,8+1,1)) | G14: =SUMIFS('Material Receipt'!$F$5:$F$6004,'Material Receipt'!$A$5:$A$6004,">="&DATE($C$4,8,1),'Material Receipt'!$A$5:$A$6004,"<"&DATE($C$4,8+1,1))
B15: Sep | C15: =SUMIFS('Batch Production'!$D$5:$D$6004,'Batch Production'!$A$5:$A$6004,">="&DATE($C$4,9,1),'Batch Production'!$A$5:$A$6004,"<"&DATE($C$4,9+1,1)) | D15: =SUMIFS('Dispatch (Challan)'!$F$5:$F$6004,'Dispatch (Challan)'!$A$5:$A$6004,">="&DATE($C$4,9,1),'Dispatch (Challan)'!$A$5:$A$6004,"<"&DATE($C$4,9+1,1)) | E15: =SUMIFS('Dispatch (Challan)'!$J$5:$J$6004,'Dispatch (Challan)'!$A$5:$A$6004,">="&DATE($C$4,9,1),'Dispatch (Challan)'!$A$5:$A$6004,"<"&DATE($C$4,9+1,1)) | F15: =SUMIFS('Payments'!$D$5:$D$6004,'Payments'!$A$5:$A$6004,">="&DATE($C$4,9,1),'Payments'!$A$5:$A$6004,"<"&DATE($C$4,9+1,1)) | G15: =SUMIFS('Material Receipt'!$F$5:$F$6004,'Material Receipt'!$A$5:$A$6004,">="&DATE($C$4,9,1),'Material Receipt'!$A$5:$A$6004,"<"&DATE($C$4,9+1,1))
B16: Oct | C16: =SUMIFS('Batch Production'!$D$5:$D$6004,'Batch Production'!$A$5:$A$6004,">="&DATE($C$4,10,1),'Batch Production'!$A$5:$A$6004,"<"&DATE($C$4,10+1,1)) | D16: =SUMIFS('Dispatch (Challan)'!$F$5:$F$6004,'Dispatch (Challan)'!$A$5:$A$6004,">="&DATE($C$4,10,1),'Dispatch (Challan)'!$A$5:$A$6004,"<"&DATE($C$4,10+1,1)) | E16: =SUMIFS('Dispatch (Challan)'!$J$5:$J$6004,'Dispatch (Challan)'!$A$5:$A$6004,">="&DATE($C$4,10,1),'Dispatch (Challan)'!$A$5:$A$6004,"<"&DATE($C$4,10+1,1)) | F16: =SUMIFS('Payments'!$D$5:$D$6004,'Payments'!$A$5:$A$6004,">="&DATE($C$4,10,1),'Payments'!$A$5:$A$6004,"<"&DATE($C$4,10+1,1)) | G16: =SUMIFS('Material Receipt'!$F$5:$F$6004,'Material Receipt'!$A$5:$A$6004,">="&DATE($C$4,10,1),'Material Receipt'!$A$5:$A$6004,"<"&DATE($C$4,10+1,1))
B17: Nov | C17: =SUMIFS('Batch Production'!$D$5:$D$6004,'Batch Production'!$A$5:$A$6004,">="&DATE($C$4,11,1),'Batch Production'!$A$5:$A$6004,"<"&DATE($C$4,11+1,1)) | D17: =SUMIFS('Dispatch (Challan)'!$F$5:$F$6004,'Dispatch (Challan)'!$A$5:$A$6004,">="&DATE($C$4,11,1),'Dispatch (Challan)'!$A$5:$A$6004,"<"&DATE($C$4,11+1,1)) | E17: =SUMIFS('Dispatch (Challan)'!$J$5:$J$6004,'Dispatch (Challan)'!$A$5:$A$6004,">="&DATE($C$4,11,1),'Dispatch (Challan)'!$A$5:$A$6004,"<"&DATE($C$4,11+1,1)) | F17: =SUMIFS('Payments'!$D$5:$D$6004,'Payments'!$A$5:$A$6004,">="&DATE($C$4,11,1),'Payments'!$A$5:$A$6004,"<"&DATE($C$4,11+1,1)) | G17: =SUMIFS('Material Receipt'!$F$5:$F$6004,'Material Receipt'!$A$5:$A$6004,">="&DATE($C$4,11,1),'Material Receipt'!$A$5:$A$6004,"<"&DATE($C$4,11+1,1))
B18: Dec | C18: =SUMIFS('Batch Production'!$D$5:$D$6004,'Batch Production'!$A$5:$A$6004,">="&DATE($C$4,12,1),'Batch Production'!$A$5:$A$6004,"<"&DATE($C$4,12+1,1)) | D18: =SUMIFS('Dispatch (Challan)'!$F$5:$F$6004,'Dispatch (Challan)'!$A$5:$A$6004,">="&DATE($C$4,12,1),'Dispatch (Challan)'!$A$5:$A$6004,"<"&DATE($C$4,12+1,1)) | E18: =SUMIFS('Dispatch (Challan)'!$J$5:$J$6004,'Dispatch (Challan)'!$A$5:$A$6004,">="&DATE($C$4,12,1),'Dispatch (Challan)'!$A$5:$A$6004,"<"&DATE($C$4,12+1,1)) | F18: =SUMIFS('Payments'!$D$5:$D$6004,'Payments'!$A$5:$A$6004,">="&DATE($C$4,12,1),'Payments'!$A$5:$A$6004,"<"&DATE($C$4,12+1,1)) | G18: =SUMIFS('Material Receipt'!$F$5:$F$6004,'Material Receipt'!$A$5:$A$6004,">="&DATE($C$4,12,1),'Material Receipt'!$A$5:$A$6004,"<"&DATE($C$4,12+1,1))
B19: TOTAL | C19: =SUM(C7:C18) | D19: =SUM(D7:D18) | E19: =SUM(E7:E18) | F19: =SUM(F7:F18) | G19: =SUM(G7:G18)

Sheet Monthly Consumption
A1: Monthly Consumption Report
A2: Month-wise raw-material consumed across the plant. Set the year.
B4: Year: | C4: 2026
B6: Month | C6: Cement (kg) | D6: Sand (kg) | E6: Agg 20mm (kg) | F6: Agg 10mm (kg) | G6: Water (ltr) | H6: Admixture (kg) | I6: Diesel (ltr)
B7: Jan | C7: =SUMIFS('Batch Production'!$F$5:$F$6004,'Batch Production'!$A$5:$A$6004,">="&DATE($C$4,1,1),'Batch Production'!$A$5:$A$6004,"<"&DATE($C$4,1+1,1)) | D7: =SUMIFS('Batch Production'!$G$5:$G$6004,'Batch Production'!$A$5:$A$6004,">="&DATE($C$4,1,1),'Batch Production'!$A$5:$A$6004,"<"&DATE($C$4,1+1,1)) | E7: =SUMIFS('Batch Production'!$H$5:$H$6004,'Batch Production'!$A$5:$A$6004,">="&DATE($C$4,1,1),'Batch Production'!$A$5:$A$6004,"<"&DATE($C$4,1+1,1)) | F7: =SUMIFS('Batch Production'!$I$5:$I$6004,'Batch Production'!$A$5:$A$6004,">="&DATE($C$4,1,1),'Batch Production'!$A$5:$A$6004,"<"&DATE($C$4,1+1,1)) | G7: =SUMIFS('Batch Production'!$J$5:$J$6004,'Batch Production'!$A$5:$A$6004,">="&DATE($C$4,1,1),'Batch Production'!$A$5:$A$6004,"<"&DATE($C$4,1+1,1)) | H7: =SUMIFS('Batch Production'!$K$5:$K$6004,'Batch Production'!$A$5:$A$6004,">="&DATE($C$4,1,1),'Batch Production'!$A$5:$A$6004,"<"&DATE($C$4,1+1,1)) | I7: =SUMIFS('Fuel Log'!$C$5:$C$6004,'Fuel Log'!$A$5:$A$6004,">="&DATE($C$4,1,1),'Fuel Log'!$A$5:$A$6004,"<"&DATE($C$4,1+1,1))
B8: Feb | C8: =SUMIFS('Batch Production'!$F$5:$F$6004,'Batch Production'!$A$5:$A$6004,">="&DATE($C$4,2,1),'Batch Production'!$A$5:$A$6004,"<"&DATE($C$4,2+1,1)) | D8: =SUMIFS('Batch Production'!$G$5:$G$6004,'Batch Production'!$A$5:$A$6004,">="&DATE($C$4,2,1),'Batch Production'!$A$5:$A$6004,"<"&DATE($C$4,2+1,1)) | E8: =SUMIFS('Batch Production'!$H$5:$H$6004,'Batch Production'!$A$5:$A$6004,">="&DATE($C$4,2,1),'Batch Production'!$A$5:$A$6004,"<"&DATE($C$4,2+1,1)) | F8: =SUMIFS('Batch Production'!$I$5:$I$6004,'Batch Production'!$A$5:$A$6004,">="&DATE($C$4,2,1),'Batch Production'!$A$5:$A$6004,"<"&DATE($C$4,2+1,1)) | G8: =SUMIFS('Batch Production'!$J$5:$J$6004,'Batch Production'!$A$5:$A$6004,">="&DATE($C$4,2,1),'Batch Production'!$A$5:$A$6004,"<"&DATE($C$4,2+1,1)) | H8: =SUMIFS('Batch Production'!$K$5:$K$6004,'Batch Production'!$A$5:$A$6004,">="&DATE($C$4,2,1),'Batch Production'!$A$5:$A$6004,"<"&DATE($C$4,2+1,1)) | I8: =SUMIFS('Fuel Log'!$C$5:$C$6004,'Fuel Log'!$A$5:$A$6004,">="&DATE($C$4,2,1),'Fuel Log'!$A$5:$A$6004,"<"&DATE($C$4,2+1,1))
B9: Mar | C9: =SUMIFS('Batch Production'!$F$5:$F$6004,'Batch Production'!$A$5:$A$6004,">="&DATE($C$4,3,1),'Batch Production'!$A$5:$A$6004,"<"&DATE($C$4,3+1,1)) | D9: =SUMIFS('Batch Production'!$G$5:$G$6004,'Batch Production'!$A$5:$A$6004,">="&DATE($C$4,3,1),'Batch Production'!$A$5:$A$6004,"<"&DATE($C$4,3+1,1)) | E9: =SUMIFS('Batch Production'!$H$5:$H$6004,'Batch Production'!$A$5:$A$6004,">="&DATE($C$4,3,1),'Batch Production'!$A$5:$A$6004,"<"&DATE($C$4,3+1,1)) | F9: =SUMIFS('Batch Production'!$I$5:$I$6004,'Batch Production'!$A$5:$A$6004,">="&DATE($C$4,3,1),'Batch Production'!$A$5:$A$6004,"<"&DATE($C$4,3+1,1)) | G9: =SUMIFS('Batch Production'!$J$5:$J$6004,'Batch Production'!$A$5:$A$6004,">="&DATE($C$4,3,1),'Batch Production'!$A$5:$A$6004,"<"&DATE($C$4,3+1,1)) | H9: =SUMIFS('Batch Production'!$K$5:$K$6004,'Batch Production'!$A$5:$A$6004,">="&DATE($C$4,3,1),'Batch Production'!$A$5:$A$6004,"<"&DATE($C$4,3+1,1)) | I9: =SUMIFS('Fuel Log'!$C$5:$C$6004,'Fuel Log'!$A$5:$A$6004,">="&DATE($C$4,3,1),'Fuel Log'!$A$5:$A$6004,"<"&DATE($C$4,3+1,1))
B10: Apr | C10: =SUMIFS('Batch Production'!$F$5:$F$6004,'Batch Production'!$A$5:$A$6004,">="&DATE($C$4,4,1),'Batch Production'!$A$5:$A$6004,"<"&DATE($C$4,4+1,1)) | D10: =SUMIFS('Batch Production'!$G$5:$G$6004,'Batch Production'!$A$5:$A$6004,">="&DATE($C$4,4,1),'Batch Production'!$A$5:$A$6004,"<"&DATE($C$4,4+1,1)) | E10: =SUMIFS('Batch Production'!$H$5:$H$6004,'Batch Production'!$A$5:$A$6004,">="&DATE($C$4,4,1),'Batch Production'!$A$5:$A$6004,"<"&DATE($C$4,4+1,1)) | F10: =SUMIFS('Batch Production'!$I$5:$I$6004,'Batch Production'!$A$5:$A$6004,">="&DATE($C$4,4,1),'Batch Production'!$A$5:$A$6004,"<"&DATE($C$4,4+1,1)) | G10: =SUMIFS('Batch Production'!$J$5:$J$6004,'Batch Production'!$A$5:$A$6004,">="&DATE($C$4,4,1),'Batch Production'!$A$5:$A$6004,"<"&DATE($C$4,4+1,1)) | H10: =SUMIFS('Batch Production'!$K$5:$K$6004,'Batch Production'!$A$5:$A$6004,">="&DATE($C$4,4,1),'Batch Production'!$A$5:$A$6004,"<"&DATE($C$4,4+1,1)) | I10: =SUMIFS('Fuel Log'!$C$5:$C$6004,'Fuel Log'!$A$5:$A$6004,">="&DATE($C$4,4,1),'Fuel Log'!$A$5:$A$6004,"<"&DATE($C$4,4+1,1))
B11: May | C11: =SUMIFS('Batch Production'!$F$5:$F$6004,'Batch Production'!$A$5:$A$6004,">="&DATE($C$4,5,1),'Batch Production'!$A$5:$A$6004,"<"&DATE($C$4,5+1,1)) | D11: =SUMIFS('Batch Production'!$G$5:$G$6004,'Batch Production'!$A$5:$A$6004,">="&DATE($C$4,5,1),'Batch Production'!$A$5:$A$6004,"<"&DATE($C$4,5+1,1)) | E11: =SUMIFS('Batch Production'!$H$5:$H$6004,'Batch Production'!$A$5:$A$6004,">="&DATE($C$4,5,1),'Batch Production'!$A$5:$A$6004,"<"&DATE($C$4,5+1,1)) | F11: =SUMIFS('Batch Production'!$I$5:$I$6004,'Batch Production'!$A$5:$A$6004,">="&DATE($C$4,5,1),'Batch Production'!$A$5:$A$6004,"<"&DATE($C$4,5+1,1)) | G11: =SUMIFS('Batch Production'!$J$5:$J$6004,'Batch Production'!$A$5:$A$6004,">="&DATE($C$4,5,1),'Batch Production'!$A$5:$A$6004,"<"&DATE($C$4,5+1,1)) | H11: =SUMIFS('Batch Production'!$K$5:$K$6004,'Batch Production'!$A$5:$A$6004,">="&DATE($C$4,5,1),'Batch Production'!$A$5:$A$6004,"<"&DATE($C$4,5+1,1)) | I11: =SUMIFS('Fuel Log'!$C$5:$C$6004,'Fuel Log'!$A$5:$A$6004,">="&DATE($C$4,5,1),'Fuel Log'!$A$5:$A$6004,"<"&DATE($C$4,5+1,1))
B12: Jun | C12: =SUMIFS('Batch Production'!$F$5:$F$6004,'Batch Production'!$A$5:$A$6004,">="&DATE($C$4,6,1),'Batch Production'!$A$5:$A$6004,"<"&DATE($C$4,6+1,1)) | D12: =SUMIFS('Batch Production'!$G$5:$G$6004,'Batch Production'!$A$5:$A$6004,">="&DATE($C$4,6,1),'Batch Production'!$A$5:$A$6004,"<"&DATE($C$4,6+1,1)) | E12: =SUMIFS('Batch Production'!$H$5:$H$6004,'Batch Production'!$A$5:$A$6004,">="&DATE($C$4,6,1),'Batch Production'!$A$5:$A$6004,"<"&DATE($C$4,6+1,1)) | F12: =SUMIFS('Batch Production'!$I$5:$I$6004,'Batch Production'!$A$5:$A$6004,">="&DATE($C$4,6,1),'Batch Production'!$A$5:$A$6004,"<"&DATE($C$4,6+1,1)) | G12: =SUMIFS('Batch Production'!$J$5:$J$6004,'Batch Production'!$A$5:$A$6004,">="&DATE($C$4,6,1),'Batch Production'!$A$5:$A$6004,"<"&DATE($C$4,6+1,1)) | H12: =SUMIFS('Batch Production'!$K$5:$K$6004,'Batch Production'!$A$5:$A$6004,">="&DATE($C$4,6,1),'Batch Production'!$A$5:$A$6004,"<"&DATE($C$4,6+1,1)) | I12: =SUMIFS('Fuel Log'!$C$5:$C$6004,'Fuel Log'!$A$5:$A$6004,">="&DATE($C$4,6,1),'Fuel Log'!$A$5:$A$6004,"<"&DATE($C$4,6+1,1))
B13: Jul | C13: =SUMIFS('Batch Production'!$F$5:$F$6004,'Batch Production'!$A$5:$A$6004,">="&DATE($C$4,7,1),'Batch Production'!$A$5:$A$6004,"<"&DATE($C$4,7+1,1)) | D13: =SUMIFS('Batch Production'!$G$5:$G$6004,'Batch Production'!$A$5:$A$6004,">="&DATE($C$4,7,1),'Batch Production'!$A$5:$A$6004,"<"&DATE($C$4,7+1,1)) | E13: =SUMIFS('Batch Production'!$H$5:$H$6004,'Batch Production'!$A$5:$A$6004,">="&DATE($C$4,7,1),'Batch Production'!$A$5:$A$6004,"<"&DATE($C$4,7+1,1)) | F13: =SUMIFS('Batch Production'!$I$5:$I$6004,'Batch Production'!$A$5:$A$6004,">="&DATE($C$4,7,1),'Batch Production'!$A$5:$A$6004,"<"&DATE($C$4,7+1,1)) | G13: =SUMIFS('Batch Production'!$J$5:$J$6004,'Batch Production'!$A$5:$A$6004,">="&DATE($C$4,7,1),'Batch Production'!$A$5:$A$6004,"<"&DATE($C$4,7+1,1)) | H13: =SUMIFS('Batch Production'!$K$5:$K$6004,'Batch Production'!$A$5:$A$6004,">="&DATE($C$4,7,1),'Batch Production'!$A$5:$A$6004,"<"&DATE($C$4,7+1,1)) | I13: =SUMIFS('Fuel Log'!$C$5:$C$6004,'Fuel Log'!$A$5:$A$6004,">="&DATE($C$4,7,1),'Fuel Log'!$A$5:$A$6004,"<"&DATE($C$4,7+1,1))
B14: Aug | C14: =SUMIFS('Batch Production'!$F$5:$F$6004,'Batch Production'!$A$5:$A$6004,">="&DATE($C$4,8,1),'Batch Production'!$A$5:$A$6004,"<"&DATE($C$4,8+1,1)) | D14: =SUMIFS('Batch Production'!$G$5:$G$6004,'Batch Production'!$A$5:$A$6004,">="&DATE($C$4,8,1),'Batch Production'!$A$5:$A$6004,"<"&DATE($C$4,8+1,1)) | E14: =SUMIFS('Batch Production'!$H$5:$H$6004,'Batch Production'!$A$5:$A$6004,">="&DATE($C$4,8,1),'Batch Production'!$A$5:$A$6004,"<"&DATE($C$4,8+1,1)) | F14: =SUMIFS('Batch Production'!$I$5:$I$6004,'Batch Production'!$A$5:$A$6004,">="&DATE($C$4,8,1),'Batch Production'!$A$5:$A$6004,"<"&DATE($C$4,8+1,1)) | G14: =SUMIFS('Batch Production'!$J$5:$J$6004,'Batch Production'!$A$5:$A$6004,">="&DATE($C$4,8,1),'Batch Production'!$A$5:$A$6004,"<"&DATE($C$4,8+1,1)) | H14: =SUMIFS('Batch Production'!$K$5:$K$6004,'Batch Production'!$A$5:$A$6004,">="&DATE($C$4,8,1),'Batch Production'!$A$5:$A$6004,"<"&DATE($C$4,8+1,1)) | I14: =SUMIFS('Fuel Log'!$C$5:$C$6004,'Fuel Log'!$A$5:$A$6004,">="&DATE($C$4,8,1),'Fuel Log'!$A$5:$A$6004,"<"&DATE($C$4,8+1,1))
B15: Sep | C15: =SUMIFS('Batch Production'!$F$5:$F$6004,'Batch Production'!$A$5:$A$6004,">="&DATE($C$4,9,1),'Batch Production'!$A$5:$A$6004,"<"&DATE($C$4,9+1,1)) | D15: =SUMIFS('Batch Production'!$G$5:$G$6004,'Batch Production'!$A$5:$A$6004,">="&DATE($C$4,9,1),'Batch Production'!$A$5:$A$6004,"<"&DATE($C$4,9+1,1)) | E15: =SUMIFS('Batch Production'!$H$5:$H$6004,'Batch Production'!$A$5:$A$6004,">="&DATE($C$4,9,1),'Batch Production'!$A$5:$A$6004,"<"&DATE($C$4,9+1,1)) | F15: =SUMIFS('Batch Production'!$I$5:$I$6004,'Batch Production'!$A$5:$A$6004,">="&DATE($C$4,9,1),'Batch Production'!$A$5:$A$6004,"<"&DATE($C$4,9+1,1)) | G15: =SUMIFS('Batch Production'!$J$5:$J$6004,'Batch Production'!$A$5:$A$6004,">="&DATE($C$4,9,1),'Batch Production'!$A$5:$A$6004,"<"&DATE($C$4,9+1,1)) | H15: =SUMIFS('Batch Production'!$K$5:$K$6004,'Batch Production'!$A$5:$A$6004,">="&DATE($C$4,9,1),'Batch Production'!$A$5:$A$6004,"<"&DATE($C$4,9+1,1)) | I15: =SUMIFS('Fuel Log'!$C$5:$C$6004,'Fuel Log'!$A$5:$A$6004,">="&DATE($C$4,9,1),'Fuel Log'!$A$5:$A$6004,"<"&DATE($C$4,9+1,1))
B16: Oct | C16: =SUMIFS('Batch Production'!$F$5:$F$6004,'Batch Production'!$A$5:$A$6004,">="&DATE($C$4,10,1),'Batch Production'!$A$5:$A$6004,"<"&DATE($C$4,10+1,1)) | D16: =SUMIFS('Batch Production'!$G$5:$G$6004,'Batch Production'!$A$5:$A$6004,">="&DATE($C$4,10,1),'Batch Production'!$A$5:$A$6004,"<"&DATE($C$4,10+1,1)) | E16: =SUMIFS('Batch Production'!$H$5:$H$6004,'Batch Production'!$A$5:$A$6004,">="&DATE($C$4,10,1),'Batch Production'!$A$5:$A$6004,"<"&DATE($C$4,10+1,1)) | F16: =SUMIFS('Batch Production'!$I$5:$I$6004,'Batch Production'!$A$5:$A$6004,">="&DATE($C$4,10,1),'Batch Production'!$A$5:$A$6004,"<"&DATE($C$4,10+1,1)) | G16: =SUMIFS('Batch Production'!$J$5:$J$6004,'Batch Production'!$A$5:$A$6004,">="&DATE($C$4,10,1),'Batch Production'!$A$5:$A$6004,"<"&DATE($C$4,10+1,1)) | H16: =SUMIFS('Batch Production'!$K$5:$K$6004,'Batch Production'!$A$5:$A$6004,">="&DATE($C$4,10,1),'Batch Production'!$A$5:$A$6004,"<"&DATE($C$4,10+1,1)) | I16: =SUMIFS('Fuel Log'!$C$5:$C$6004,'Fuel Log'!$A$5:$A$6004,">="&DATE($C$4,10,1),'Fuel Log'!$A$5:$A$6004,"<"&DATE($C$4,10+1,1))
B17: Nov | C17: =SUMIFS('Batch Production'!$F$5:$F$6004,'Batch Production'!$A$5:$A$6004,">="&DATE($C$4,11,1),'Batch Production'!$A$5:$A$6004,"<"&DATE($C$4,11+1,1)) | D17: =SUMIFS('Batch Production'!$G$5:$G$6004,'Batch Production'!$A$5:$A$6004,">="&DATE($C$4,11,1),'Batch Production'!$A$5:$A$6004,"<"&DATE($C$4,11+1,1)) | E17: =SUMIFS('Batch Production'!$H$5:$H$6004,'Batch Production'!$A$5:$A$6004,">="&DATE($C$4,11,1),'Batch Production'!$A$5:$A$6004,"<"&DATE($C$4,11+1,1)) | F17: =SUMIFS('Batch Production'!$I$5:$I$6004,'Batch Production'!$A$5:$A$6004,">="&DATE($C$4,11,1),'Batch Production'!$A$5:$A$6004,"<"&DATE($C$4,11+1,1)) | G17: =SUMIFS('Batch Production'!$J$5:$J$6004,'Batch Production'!$A$5:$A$6004,">="&DATE($C$4,11,1),'Batch Production'!$A$5:$A$6004,"<"&DATE($C$4,11+1,1)) | H17: =SUMIFS('Batch Production'!$K$5:$K$6004,'Batch Production'!$A$5:$A$6004,">="&DATE($C$4,11,1),'Batch Production'!$A$5:$A$6004,"<"&DATE($C$4,11+1,1)) | I17: =SUMIFS('Fuel Log'!$C$5:$C$6004,'Fuel Log'!$A$5:$A$6004,">="&DATE($C$4,11,1),'Fuel Log'!$A$5:$A$6004,"<"&DATE($C$4,11+1,1))
B18: Dec | C18: =SUMIFS('Batch Production'!$F$5:$F$6004,'Batch Production'!$A$5:$A$6004,">="&DATE($C$4,12,1),'Batch Production'!$A$5:$A$6004,"<"&DATE($C$4,12+1,1)) | D18: =SUMIFS('Batch Production'!$G$5:$G$6004,'Batch Production'!$A$5:$A$6004,">="&DATE($C$4,12,1),'Batch Production'!$A$5:$A$6004,"<"&DATE($C$4,12+1,1)) | E18: =SUMIFS('Batch Production'!$H$5:$H$6004,'Batch Production'!$A$5:$A$6004,">="&DATE($C$4,12,1),'Batch Production'!$A$5:$A$6004,"<"&DATE($C$4,12+1,1)) | F18: =SUMIFS('Batch Production'!$I$5:$I$6004,'Batch Production'!$A$5:$A$6004,">="&DATE($C$4,12,1),'Batch Production'!$A$5:$A$6004,"<"&DATE($C$4,12+1,1)) | G18: =SUMIFS('Batch Production'!$J$5:$J$6004,'Batch Production'!$A$5:$A$6004,">="&DATE($C$4,12,1),'Batch Production'!$A$5:$A$6004,"<"&DATE($C$4,12+1,1)) | H18: =SUMIFS('Batch Production'!$K$5:$K$6004,'Batch Production'!$A$5:$A$6004,">="&DATE($C$4,12,1),'Batch Production'!$A$5:$A$6004,"<"&DATE($C$4,12+1,1)) | I18: =SUMIFS('Fuel Log'!$C$5:$C$6004,'Fuel Log'!$A$5:$A$6004,">="&DATE($C$4,12,1),'Fuel Log'!$A$5:$A$6004,"<"&DATE($C$4,12+1,1))
B19: TOTAL | C19: =SUM(C7:C18) | D19: =SUM(D7:D18) | E19: =SUM(E7:E18) | F19: =SUM(F7:F18) | G19: =SUM(G7:G18) | H19: =SUM(H7:H18) | I19: =SUM(I7:I18)

Sheet Setup - Clients
A1: Setup - Clients
A2: Customer master. Add each client once; orders, challans & payments pick from here.
A4: Client / Company Name | B4: Contact Person | C4: Phone | D4: GST No. | E4: Billing Address
A5: DB INFRATECH | B5: Mr. Pritam Keni | C5: 9769030312
A6: DS INFRASTRUCTURE | B6: Er. Aadesh Kakde | C6: 9766921554
A7: URVI ENTERPRISES | B7: Mr. Bunty Dhamale | C7: 9699815155
A8: HIRAWATI AGRO PVT LTD | B8: Mr. Narayan Ji | C8: 8879805815
A9: AANANTH CORPORATION | B9: Mr. Narayan Ji | C9: 8879805815
A10: DDSR KALAMBOLI | B10: Mr. Pankaj sir | C10: 7741808216
A11: DDSR KHARGHAR | B11: Mr. Pankaj sir | C11: 7741808216
A12: LANDMARK ( ROYAL INFRA) | B12: Er. Akshay Sir | C12: 9021225823

Sheet Setup - Mix Design
A1: Setup - Mix Design
A2: Concrete grades & material per m3. Drives production consumption + selling rate. Edit to your design.
A4: Grade | B4: Cement (kg/m3) | C4: Sand (kg/m3) | D4: Aggregate 20mm (kg/m3) | E4: Aggregate 10mm (kg/m3) | F4: Water (ltr/m3) | G4: Admixture (kg/m3) | H4: W/C Ratio | I4: Selling Rate (₹/m3)
A5: M15 | B5: 320 | C5: 750 | D5: 700 | E5: 480 | F5: 160 | G5: 1.6 | H5: =IF(B5="","",ROUND(F5/B5,2)) | I5: 4200
A6: M20 | B6: 360 | C6: 720 | D6: 720 | E6: 480 | F6: 170 | G6: 2 | H6: =IF(B6="","",ROUND(F6/B6,2)) | I6: 4600
A7: M25 | B7: 400 | C7: 690 | D7: 730 | E7: 490 | F7: 175 | G7: 2.4 | H7: =IF(B7="","",ROUND(F7/B7,2)) | I7: 5000
A8: M30 | B8: 440 | C8: 660 | D8: 740 | E8: 500 | F8: 180 | G8: 3.1 | H8: =IF(B8="","",ROUND(F8/B8,2)) | I8: 5400
A9: M35 | B9: 480 | C9: 630 | D9: 750 | E9: 510 | F9: 185 | G9: 3.8 | H9: =IF(B9="","",ROUND(F9/B9,2)) | I9: 5900
A10: M40 | B10: 520 | C10: 600 | D10: 760 | E10: 520 | F10: 190 | G10: 4.7 | H10: =IF(B10="","",ROUND(F10/B10,2)) | I10: 6400
H11: =IF(B11="","",ROUND(F11/B11,2))
H12: =IF(B12="","",ROUND(F12/B12,2))
H13: =IF(B13="","",ROUND(F13/B13,2))
H14: =IF(B14="","",ROUND(F14/B14,2))
H15: =IF(B15="","",ROUND(F15/B15,2))
H16: =IF(B16="","",ROUND(F16/B16,2))
H17: =IF(B17="","",ROUND(F17/B17,2))
H18: =IF(B18="","",ROUND(F18/B18,2))
H19: =IF(B19="","",ROUND(F19/B19,2))
H20: =IF(B20="","",ROUND(F20/B20,2))
H21: =IF(B21="","",ROUND(F21/B21,2))
H22: =IF(B22="","",ROUND(F22/B22,2))
... H504: =IF(B504="","",ROUND(F504/B504,2))

Sheet Setup - Vehicles
A1: Setup - Vehicles
A2: Transit mixer / pump fleet. Dispatch picks the vehicle; driver auto-fills.
A4: Vehicle No. | B4: Type | C4: Capacity (m3) | D4: Default Driver | E4: Status
A5: MH 46 DC 0813 | B5: Transit Mixer | C5: 7 M³ | D5: RANJEET | E5: Active
A6: MH 46 DC 0814 | B6: Transit Mixer | C6: 7 M³ | D6: MANOJ | E6: Active
A7: MH 46 BB 9003 | B7: Transit Mixer | C7: 6 M³ | D7: SUBHASH | E7: Active
A8: MH 48 T 5967 | B8: Transit Mixer | C8: 6 M³ | D8: MAMA | E8: Active
A9: MH 46 BP 0826 | B9: Transit Mixer | C9: 6 M³ | D9: KAMAL | E9: Active

Sheet Setup - Drivers
A1: Setup - Drivers
A2: Driver master.
A4: Driver Name | B4: Phone | C4: Licence No. | D4: Notes
A5: RANJEET | B5: 7394924413
A6: MANOJ | B6: 8879446133
A7: SUBHASH | B7: 9309133983
A8: MAMA | B8: 9987366558
A9: KAMAL | B9: 8828920771

Sheet Setup - Materials
A1: Setup - Materials
A2: Raw material master: opening stock, rate & reorder level. Drives the Stock Register + low-stock alerts.
A4: Material | B4: Unit | C4: Opening Stock | D4: Purchase Rate (₹/unit) | E4: Reorder Level
A5: Cement | B5: kg | C5: 0 | D5: 6.3 | E5: 20000
A6: Sand | B6: kg | C6: 0 | D6: 0.82 | E6: 40000
A7: Aggregate 20mm | B7: kg | C7: 0 | D7: 0.72 | E7: 40000
A8: Aggregate 10mm | B8: kg | C8: 0 | D8: 0.72 | E8: 25000
A9: Admixture | B9: kg | C9: 0 | D9: 5.4 | E9: 200
A10: Diesel | B10: ltr | C10: 0 | D10: 98.4 | E10: 500

Sheet Orders
A1: Orders - Daily Order Book
A2: Pick client & grade. Rate, value, delivered qty, balance & status auto-calculate.
A4: Date | B4: Order No. | C4: Client | D4: Site / Location | E4: Grade | F4: Qty (m3) | G4: Rate (₹/m3) | H4: Order Value (₹) | I4: Delivered (m3) | J4: Balance (m3) | K4: Status
G5: =IFERROR(IF(E5="","",VLOOKUP(E5,'Setup - Mix Design'!$A$5:$I$504,9,0)),"") | H5: =IF(OR(F5="",G5=""),"",F5*G5) | I5: =IF(B5="","",SUMIF('Dispatch (Challan)'!$C$5:$C$6004,B5,'Dispatch (Challan)'!$F$5:$F$6004)) | J5: =IF(F5="","",F5-I5) | K5: =IF(F5="","",IF(I5=0,"Pending",IF(I5>=F5,"Completed","Partial")))
G6: =IFERROR(IF(E6="","",VLOOKUP(E6,'Setup - Mix Design'!$A$5:$I$504,9,0)),"") | H6: =IF(OR(F6="",G6=""),"",F6*G6) | I6: =IF(B6="","",SUMIF('Dispatch (Challan)'!$C$5:$C$6004,B6,'Dispatch (Challan)'!$F$5:$F$6004)) | J6: =IF(F6="","",F6-I6) | K6: =IF(F6="","",IF(I6=0,"Pending",IF(I6>=F6,"Completed","Partial")))
G7: =IFERROR(IF(E7="","",VLOOKUP(E7,'Setup - Mix Design'!$A$5:$I$504,9,0)),"") | H7: =IF(OR(F7="",G7=""),"",F7*G7) | I7: =IF(B7="","",SUMIF('Dispatch (Challan)'!$C$5:$C$6004,B7,'Dispatch (Challan)'!$F$5:$F$6004)) | J7: =IF(F7="","",F7-I7) | K7: =IF(F7="","",IF(I7=0,"Pending",IF(I7>=F7,"Completed","Partial")))
G8: =IFERROR(IF(E8="","",VLOOKUP(E8,'Setup - Mix Design'!$A$5:$I$504,9,0)),"") | H8: =IF(OR(F8="",G8=""),"",F8*G8) | I8: =IF(B8="","",SUMIF('Dispatch (Challan)'!$C$5:$C$6004,B8,'Dispatch (Challan)'!$F$5:$F$6004)) | J8: =IF(F8="","",F8-I8) | K8: =IF(F8="","",IF(I8=0,"Pending",IF(I8>=F8,"Completed","Partial")))
G9: =IFERROR(IF(E9="","",VLOOKUP(E9,'Setup - Mix Design'!$A$5:$I$504,9,0)),"") | H9: =IF(OR(F9="",G9=""),"",F9*G9) | I9: =IF(B9="","",SUMIF('Dispatch (Challan)'!$C$5:$C$6004,B9,'Dispatch (Challan)'!$F$5:$F$6004)) | J9: =IF(F9="","",F9-I9) | K9: =IF(F9="","",IF(I9=0,"Pending",IF(I9>=F9,"Completed","Partial")))
G10: =IFERROR(IF(E10="","",VLOOKUP(E10,'Setup - Mix Design'!$A$5:$I$504,9,0)),"") | H10: =IF(OR(F10="",G10=""),"",F10*G10) | I10: =IF(B10="","",SUMIF('Dispatch (Challan)'!$C$5:$C$6004,B10,'Dispatch (Challan)'!$F$5:$F$6004)) | J10: =IF(F10="","",F10-I10) | K10: =IF(F10="","",IF(I10=0,"Pending",IF(I10>=F10,"Completed","Partial")))
G11: =IFERROR(IF(E11="","",VLOOKUP(E11,'Setup - Mix Design'!$A$5:$I$504,9,0)),"") | H11: =IF(OR(F11="",G11=""),"",F11*G11) | I11: =IF(B11="","",SUMIF('Dispatch (Challan)'!$C$5:$C$6004,B11,'Dispatch (Challan)'!$F$5:$F$6004)) | J11: =IF(F11="","",F11-I11) | K11: =IF(F11="","",IF(I11=0,"Pending",IF(I11>=F11,"Completed","Partial")))
G12: =IFERROR(IF(E12="","",VLOOKUP(E12,'Setup - Mix Design'!$A$5:$I$504,9,0)),"") | H12: =IF(OR(F12="",G12=""),"",F12*G12) | I12: =IF(B12="","",SUMIF('Dispatch (Challan)'!$C$5:$C$6004,B12,'Dispatch (Challan)'!$F$5:$F$6004)) | J12: =IF(F12="","",F12-I12) | K12: =IF(F12="","",IF(I12=0,"Pending",IF(I12>=F12,"Completed","Partial")))
G13: =IFERROR(IF(E13="","",VLOOKUP(E13,'Setup - Mix Design'!$A$5:$I$504,9,0)),"") | H13: =IF(OR(F13="",G13=""),"",F13*G13) | I13: =IF(B13="","",SUMIF('Dispatch (Challan)'!$C$5:$C$6004,B13,'Dispatch (Challan)'!$F$5:$F$6004)) | J13: =IF(F13="","",F13-I13) | K13: =IF(F13="","",IF(I13=0,"Pending",IF(I13>=F13,"Completed","Partial")))
G14: =IFERROR(IF(E14="","",VLOOKUP(E14,'Setup - Mix Design'!$A$5:$I$504,9,0)),"") | H14: =IF(OR(F14="",G14=""),"",F14*G14) | I14: =IF(B14="","",SUMIF('Dispatch (Challan)'!$C$5:$C$6004,B14,'Dispatch (Challan)'!$F$5:$F$6004)) | J14: =IF(F14="","",F14-I14) | K14: =IF(F14="","",IF(I14=0,"Pending",IF(I14>=F14,"Completed","Partial")))
G15: =IFERROR(IF(E15="","",VLOOKUP(E15,'Setup - Mix Design'!$A$5:$I$504,9,0)),"") | H15: =IF(OR(F15="",G15=""),"",F15*G15) | I15: =IF(B15="","",SUMIF('Dispatch (Challan)'!$C$5:$C$6004,B15,'Dispatch (Challan)'!$F$5:$F$6004)) | J15: =IF(F15="","",F15-I15) | K15: =IF(F15="","",IF(I15=0,"Pending",IF(I15>=F15,"Completed","Partial")))
G16: =IFERROR(IF(E16="","",VLOOKUP(E16,'Setup - Mix Design'!$A$5:$I$504,9,0)),"") | H16: =IF(OR(F16="",G16=""),"",F16*G16) | I16: =IF(B16="","",SUMIF('Dispatch (Challan)'!$C$5:$C$6004,B16,'Dispatch (Challan)'!$F$5:$F$6004)) | J16: =IF(F16="","",F16-I16) | K16: =IF(F16="","",IF(I16=0,"Pending",IF(I16>=F16,"Completed","Partial")))
... G6004: =IFERROR(IF(E6004="","",VLOOKUP(E6004,'Setup - Mix Design'!$A$5:$I$504,9,0)),"") | H6004: =IF(OR(F6004="",G6004=""),"",F6004*G6004) | I6004: =IF(B6004="","",SUMIF('Dispatch (Challan)'!$C$5:$C$6004,B6004,'Dispatch (Challan)'!$F$5:$F$6004)) | J6004: =IF(F6004="","",F6004-I6004) | K6004: =IF(F6004="","",IF(I6004=0,"Pending",IF(I6004>=F6004,"Completed","Partial")))

Sheet Dispatch (Challan)
A1: Dispatch - Challans
A2: Pick client / grade / vehicle; driver, rate & amount auto-fill. Delivered qty rolls up to Orders.
A4: Date | B4: Challan No. | C4: Order No. | D4: Client | E4: Grade | F4: Qty (m3) | G4: Vehicle No. | H4: Driver | I4: Rate (₹/m3) | J4: Amount (₹) | K4: Status
H5: =IFERROR(IF(G5="","",VLOOKUP(G5,'Setup - Vehicles'!$A$5:$D$504,4,0)),"") | I5: =IFERROR(IF(E5="","",VLOOKUP(E5,'Setup - Mix Design'!$A$5:$I$504,9,0)),"") | J5: =IF(OR(F5="",I5=""),"",F5*I5)
H6: =IFERROR(IF(G6="","",VLOOKUP(G6,'Setup - Vehicles'!$A$5:$D$504,4,0)),"") | I6: =IFERROR(IF(E6="","",VLOOKUP(E6,'Setup - Mix Design'!$A$5:$I$504,9,0)),"") | J6: =IF(OR(F6="",I6=""),"",F6*I6)
H7: =IFERROR(IF(G7="","",VLOOKUP(G7,'Setup - Vehicles'!$A$5:$D$504,4,0)),"") | I7: =IFERROR(IF(E7="","",VLOOKUP(E7,'Setup - Mix Design'!$A$5:$I$504,9,0)),"") | J7: =IF(OR(F7="",I7=""),"",F7*I7)
H8: =IFERROR(IF(G8="","",VLOOKUP(G8,'Setup - Vehicles'!$A$5:$D$504,4,0)),"") | I8: =IFERROR(IF(E8="","",VLOOKUP(E8,'Setup - Mix Design'!$A$5:$I$504,9,0)),"") | J8: =IF(OR(F8="",I8=""),"",F8*I8)
H9: =IFERROR(IF(G9="","",VLOOKUP(G9,'Setup - Vehicles'!$A$5:$D$504,4,0)),"") | I9: =IFERROR(IF(E9="","",VLOOKUP(E9,'Setup - Mix Design'!$A$5:$I$504,9,0)),"") | J9: =IF(OR(F9="",I9=""),"",F9*I9)
H10: =IFERROR(IF(G10="","",VLOOKUP(G10,'Setup - Vehicles'!$A$5:$D$504,4,0)),"") | I10: =IFERROR(IF(E10="","",VLOOKUP(E10,'Setup - Mix Design'!$A$5:$I$504,9,0)),"") | J10: =IF(OR(F10="",I10=""),"",F10*I10)
H11: =IFERROR(IF(G11="","",VLOOKUP(G11,'Setup - Vehicles'!$A$5:$D$504,4,0)),"") | I11: =IFERROR(IF(E11="","",VLOOKUP(E11,'Setup - Mix Design'!$A$5:$I$504,9,0)),"") | J11: =IF(OR(F11="",I11=""),"",F11*I11)
H12: =IFERROR(IF(G12="","",VLOOKUP(G12,'Setup - Vehicles'!$A$5:$D$504,4,0)),"") | I12: =IFERROR(IF(E12="","",VLOOKUP(E12,'Setup - Mix Design'!$A$5:$I$504,9,0)),"") | J12: =IF(OR(F12="",I12=""),"",F12*I12)
H13: =IFERROR(IF(G13="","",VLOOKUP(G13,'Setup - Vehicles'!$A$5:$D$504,4,0)),"") | I13: =IFERROR(IF(E13="","",VLOOKUP(E13,'Setup - Mix Design'!$A$5:$I$504,9,0)),"") | J13: =IF(OR(F13="",I13=""),"",F13*I13)
H14: =IFERROR(IF(G14="","",VLOOKUP(G14,'Setup - Vehicles'!$A$5:$D$504,4,0)),"") | I14: =IFERROR(IF(E14="","",VLOOKUP(E14,'Setup - Mix Design'!$A$5:$I$504,9,0)),"") | J14: =IF(OR(F14="",I14=""),"",F14*I14)
H15: =IFERROR(IF(G15="","",VLOOKUP(G15,'Setup - Vehicles'!$A$5:$D$504,4,0)),"") | I15: =IFERROR(IF(E15="","",VLOOKUP(E15,'Setup - Mix Design'!$A$5:$I$504,9,0)),"") | J15: =IF(OR(F15="",I15=""),"",F15*I15)
H16: =IFERROR(IF(G16="","",VLOOKUP(G16,'Setup - Vehicles'!$A$5:$D$504,4,0)),"") | I16: =IFERROR(IF(E16="","",VLOOKUP(E16,'Setup - Mix Design'!$A$5:$I$504,9,0)),"") | J16: =IF(OR(F16="",I16=""),"",F16*I16)
... H6004: =IFERROR(IF(G6004="","",VLOOKUP(G6004,'Setup - Vehicles'!$A$5:$D$504,4,0)),"") | I6004: =IFERROR(IF(E6004="","",VLOOKUP(E6004,'Setup - Mix Design'!$A$5:$I$504,9,0)),"") | J6004: =IF(OR(F6004="",I6004=""),"",F6004*I6004)

Sheet Challan
A1: CONCRETE KING
A2: DELIVERY CHALLAN • Ready-Mix Concrete
B4: Select Challan No: | F4: Pick a challan → every field below fills in.
B6: Challan No | C6: =$C$4 | F6: Date | G6: =IFERROR(IF($C$4="","",INDEX('Dispatch (Challan)'!$A$5:$A$6004,MATCH($C$4,'Dispatch (Challan)'!$B$5:$B$6004,0))),"")
B7: Order No | C7: =IFERROR(IF($C$4="","",INDEX('Dispatch (Challan)'!$C$5:$C$6004,MATCH($C$4,'Dispatch (Challan)'!$B$5:$B$6004,0))),"") | F7: Status | G7: =IFERROR(IF($C$4="","",INDEX('Dispatch (Challan)'!$K$5:$K$6004,MATCH($C$4,'Dispatch (Challan)'!$B$5:$B$6004,0))),"")
B8: Grade | C8: =IFERROR(IF($C$4="","",INDEX('Dispatch (Challan)'!$E$5:$E$6004,MATCH($C$4,'Dispatch (Challan)'!$B$5:$B$6004,0))),"") | F8: Vehicle No | G8: =IFERROR(IF($C$4="","",INDEX('Dispatch (Challan)'!$G$5:$G$6004,MATCH($C$4,'Dispatch (Challan)'!$B$5:$B$6004,0))),"")
B9: Quantity (m³) | C9: =IFERROR(IF($C$4="","",INDEX('Dispatch (Challan)'!$F$5:$F$6004,MATCH($C$4,'Dispatch (Challan)'!$B$5:$B$6004,0))),"") | F9: Driver | G9: =IFERROR(IF($C$4="","",INDEX('Dispatch (Challan)'!$H$5:$H$6004,MATCH($C$4,'Dispatch (Challan)'!$B$5:$B$6004,0))),"")
B10: Rate (₹/m³) | C10: =IFERROR(IF($C$4="","",INDEX('Dispatch (Challan)'!$I$5:$I$6004,MATCH($C$4,'Dispatch (Challan)'!$B$5:$B$6004,0))),"") | F10: Amount (₹) | G10: =IFERROR(IF($C$4="","",INDEX('Dispatch (Challan)'!$J$5:$J$6004,MATCH($C$4,'Dispatch (Challan)'!$B$5:$B$6004,0))),"")
B12: CUSTOMER DETAILS
B13: Customer | C13: =IFERROR(IF($C$4="","",INDEX('Dispatch (Challan)'!$D$5:$D$6004,MATCH($C$4,'Dispatch (Challan)'!$B$5:$B$6004,0))),"") | F13: Contact | G13: =IFERROR(IF($C$4="","",VLOOKUP($C$13,'Setup - Clients'!$A$5:$E$504,2,0)),"")
B14: Phone | C14: =IFERROR(IF($C$4="","",VLOOKUP($C$13,'Setup - Clients'!$A$5:$E$504,3,0)),"") | F14: GST No | G14: =IFERROR(IF($C$4="","",VLOOKUP($C$13,'Setup - Clients'!$A$5:$E$504,4,0)),"")
B15: Site / Location | C15: =IFERROR(IF($C$7="","",VLOOKUP($C$7,'Orders'!$B$5:$D$6004,3,0)),"")
B17: __________________ | F17: __________________
B18: Received in good condition | F18: Authorised Signatory
B20: =HYPERLINK("https://wa.me/"&IF($C$14="","","91"&$C$14)&"?text="&SUBSTITUTE("*CONCRETE KING - Delivery Challan*%0AChallan No: "&$C$4&"%0ADate: "&TEXT($G$6,"dd-mmm-yyyy")&"%0ACustomer: "&$C$13&"%0AGrade: "&$C$8&"%0AQty: "&$C$9&" m3%0AVehicle: "&$G$8&"%0ADriver: "&$G$9&"%0ARate: Rs "&$C$10&"%0AAmount: Rs "&$G$10," ","%20"),"📲 Send Challan on WhatsApp") | F20: 🖨 Press Ctrl+P (phone: Share ▸ Print) to Print / Save as PDF

Sheet Batch Production
A1: Batch Production - Material Consumption
A2: Enter grade + m3 only. Material consumed auto-computes from Mix Design and feeds Stock.
A4: Date | B4: Batch No. | C4: Grade | D4: Qty (m3) | E4: Operator | F4: Cement (kg) | G4: Sand (kg) | H4: Agg 20mm (kg) | I4: Agg 10mm (kg) | J4: Water (ltr) | K4: Admixture (kg)
F5: =IFERROR(IF(OR(C5="",D5=""),"",D5*VLOOKUP(C5,'Setup - Mix Design'!$A$5:$I$504,2,0)),"") | G5: =IFERROR(IF(OR(C5="",D5=""),"",D5*VLOOKUP(C5,'Setup - Mix Design'!$A$5:$I$504,3,0)),"") | H5: =IFERROR(IF(OR(C5="",D5=""),"",D5*VLOOKUP(C5,'Setup - Mix Design'!$A$5:$I$504,4,0)),"") | I5: =IFERROR(IF(OR(C5="",D5=""),"",D5*VLOOKUP(C5,'Setup - Mix Design'!$A$5:$I$504,5,0)),"") | J5: =IFERROR(IF(OR(C5="",D5=""),"",D5*VLOOKUP(C5,'Setup - Mix Design'!$A$5:$I$504,6,0)),"") | K5: =IFERROR(IF(OR(C5="",D5=""),"",D5*VLOOKUP(C5,'Setup - Mix Design'!$A$5:$I$504,7,0)),"")
F6: =IFERROR(IF(OR(C6="",D6=""),"",D6*VLOOKUP(C6,'Setup - Mix Design'!$A$5:$I$504,2,0)),"") | G6: =IFERROR(IF(OR(C6="",D6=""),"",D6*VLOOKUP(C6,'Setup - Mix Design'!$A$5:$I$504,3,0)),"") | H6: =IFERROR(IF(OR(C6="",D6=""),"",D6*VLOOKUP(C6,'Setup - Mix Design'!$A$5:$I$504,4,0)),"") | I6: =IFERROR(IF(OR(C6="",D6=""),"",D6*VLOOKUP(C6,'Setup - Mix Design'!$A$5:$I$504,5,0)),"") | J6: =IFERROR(IF(OR(C6="",D6=""),"",D6*VLOOKUP(C6,'Setup - Mix Design'!$A$5:$I$504,6,0)),"") | K6: =IFERROR(IF(OR(C6="",D6=""),"",D6*VLOOKUP(C6,'Setup - Mix Design'!$A$5:$I$504,7,0)),"")
F7: =IFERROR(IF(OR(C7="",D7=""),"",D7*VLOOKUP(C7,'Setup - Mix Design'!$A$5:$I$504,2,0)),"") | G7: =IFERROR(IF(OR(C7="",D7=""),"",D7*VLOOKUP(C7,'Setup - Mix Design'!$A$5:$I$504,3,0)),"") | H7: =IFERROR(IF(OR(C7="",D7=""),"",D7*VLOOKUP(C7,'Setup - Mix Design'!$A$5:$I$504,4,0)),"") | I7: =IFERROR(IF(OR(C7="",D7=""),"",D7*VLOOKUP(C7,'Setup - Mix Design'!$A$5:$I$504,5,0)),"") | J7: =IFERROR(IF(OR(C7="",D7=""),"",D7*VLOOKUP(C7,'Setup - Mix Design'!$A$5:$I$504,6,0)),"") | K7: =IFERROR(IF(OR(C7="",D7=""),"",D7*VLOOKUP(C7,'Setup - Mix Design'!$A$5:$I$504,7,0)),"")
F8: =IFERROR(IF(OR(C8="",D8=""),"",D8*VLOOKUP(C8,'Setup - Mix Design'!$A$5:$I$504,2,0)),"") | G8: =IFERROR(IF(OR(C8="",D8=""),"",D8*VLOOKUP(C8,'Setup - Mix Design'!$A$5:$I$504,3,0)),"") | H8: =IFERROR(IF(OR(C8="",D8=""),"",D8*VLOOKUP(C8,'Setup - Mix Design'!$A$5:$I$504,4,0)),"") | I8: =IFERROR(IF(OR(C8="",D8=""),"",D8*VLOOKUP(C8,'Setup - Mix Design'!$A$5:$I$504,5,0)),"") | J8: =IFERROR(IF(OR(C8="",D8=""),"",D8*VLOOKUP(C8,'Setup - Mix Design'!$A$5:$I$504,6,0)),"") | K8: =IFERROR(IF(OR(C8="",D8=""),"",D8*VLOOKUP(C8,'Setup - Mix Design'!$A$5:$I$504,7,0)),"")
F9: =IFERROR(IF(OR(C9="",D9=""),"",D9*VLOOKUP(C9,'Setup - Mix Design'!$A$5:$I$504,2,0)),"") | G9: =IFERROR(IF(OR(C9="",D9=""),"",D9*VLOOKUP(C9,'Setup - Mix Design'!$A$5:$I$504,3,0)),"") | H9: =IFERROR(IF(OR(C9="",D9=""),"",D9*VLOOKUP(C9,'Setup - Mix Design'!$A$5:$I$504,4,0)),"") | I9: =IFERROR(IF(OR(C9="",D9=""),"",D9*VLOOKUP(C9,'Setup - Mix Design'!$A$5:$I$504,5,0)),"") | J9: =IFERROR(IF(OR(C9="",D9=""),"",D9*VLOOKUP(C9,'Setup - Mix Design'!$A$5:$I$504,6,0)),"") | K9: =IFERROR(IF(OR(C9="",D9=""),"",D9*VLOOKUP(C9,'Setup - Mix Design'!$A$5:$I$504,7,0)),"")
F10: =IFERROR(IF(OR(C10="",D10=""),"",D10*VLOOKUP(C10,'Setup - Mix Design'!$A$5:$I$504,2,0)),"") | G10: =IFERROR(IF(OR(C10="",D10=""),"",D10*VLOOKUP(C10,'Setup - Mix Design'!$A$5:$I$504,3,0)),"") | H10: =IFERROR(IF(OR(C10="",D10=""),"",D10*VLOOKUP(C10,'Setup - Mix Design'!$A$5:$I$504,4,0)),"") | I10: =IFERROR(IF(OR(C10="",D10=""),"",D10*VLOOKUP(C10,'Setup - Mix Design'!$A$5:$I$504,5,0)),"") | J10: =IFERROR(IF(OR(C10="",D10=""),"",D10*VLOOKUP(C10,'Setup - Mix Design'!$A$5:$I$504,6,0)),"") | K10: =IFERROR(IF(OR(C10="",D10=""),"",D10*VLOOKUP(C10,'Setup - Mix Design'!$A$5:$I$504,7,0)),"")
F11: =IFERROR(IF(OR(C11="",D11=""),"",D11*VLOOKUP(C11,'Setup - Mix Design'!$A$5:$I$504,2,0)),"") | G11: =IFERROR(IF(OR(C11="",D11=""),"",D11*VLOOKUP(C11,'Setup - Mix Design'!$A$5:$I$504,3,0)),"") | H11: =IFERROR(IF(OR(C11="",D11=""),"",D11*VLOOKUP(C11,'Setup - Mix Design'!$A$5:$I$504,4,0)),"") | I11: =IFERROR(IF(OR(C11="",D11=""),"",D11*VLOOKUP(C11,'Setup - Mix Design'!$A$5:$I$504,5,0)),"") | J11: =IFERROR(IF(OR(C11="",D11=""),"",D11*VLOOKUP(C11,'Setup - Mix Design'!$A$5:$I$504,6,0)),"") | K11: =IFERROR(IF(OR(C11="",D11=""),"",D11*VLOOKUP(C11,'Setup - Mix Design'!$A$5:$I$504,7,0)),"")
F12: =IFERROR(IF(OR(C12="",D12=""),"",D12*VLOOKUP(C12,'Setup - Mix Design'!$A$5:$I$504,2,0)),"") | G12: =IFERROR(IF(OR(C12="",D12=""),"",D12*VLOOKUP(C12,'Setup - Mix Design'!$A$5:$I$504,3,0)),"") | H12: =IFERROR(IF(OR(C12="",D12=""),"",D12*VLOOKUP(C12,'Setup - Mix Design'!$A$5:$I$504,4,0)),"") | I12: =IFERROR(IF(OR(C12="",D12=""),"",D12*VLOOKUP(C12,'Setup - Mix Design'!$A$5:$I$504,5,0)),"") | J12: =IFERROR(IF(OR(C12="",D12=""),"",D12*VLOOKUP(C12,'Setup - Mix Design'!$A$5:$I$504,6,0)),"") | K12: =IFERROR(IF(OR(C12="",D12=""),"",D12*VLOOKUP(C12,'Setup - Mix Design'!$A$5:$I$504,7,0)),"")
F13: =IFERROR(IF(OR(C13="",D13=""),"",D13*VLOOKUP(C13,'Setup - Mix Design'!$A$5:$I$504,2,0)),"") | G13: =IFERROR(IF(OR(C13="",D13=""),"",D13*VLOOKUP(C13,'Setup - Mix Design'!$A$5:$I$504,3,0)),"") | H13: =IFERROR(IF(OR(C13="",D13=""),"",D13*VLOOKUP(C13,'Setup - Mix Design'!$A$5:$I$504,4,0)),"") | I13: =IFERROR(IF(OR(C13="",D13=""),"",D13*VLOOKUP(C13,'Setup - Mix Design'!$A$5:$I$504,5,0)),"") | J13: =IFERROR(IF(OR(C13="",D13=""),"",D13*VLOOKUP(C13,'Setup - Mix Design'!$A$5:$I$504,6,0)),"") | K13: =IFERROR(IF(OR(C13="",D13=""),"",D13*VLOOKUP(C13,'Setup - Mix Design'!$A$5:$I$504,7,0)),"")
F14: =IFERROR(IF(OR(C14="",D14=""),"",D14*VLOOKUP(C14,'Setup - Mix Design'!$A$5:$I$504,2,0)),"") | G14: =IFERROR(IF(OR(C14="",D14=""),"",D14*VLOOKUP(C14,'Setup - Mix Design'!$A$5:$I$504,3,0)),"") | H14: =IFERROR(IF(OR(C14="",D14=""),"",D14*VLOOKUP(C14,'Setup - Mix Design'!$A$5:$I$504,4,0)),"") | I14: =IFERROR(IF(OR(C14="",D14=""),"",D14*VLOOKUP(C14,'Setup - Mix Design'!$A$5:$I$504,5,0)),"") | J14: =IFERROR(IF(OR(C14="",D14=""),"",D14*VLOOKUP(C14,'Setup - Mix Design'!$A$5:$I$504,6,0)),"") | K14: =IFERROR(IF(OR(C14="",D14=""),"",D14*VLOOKUP(C14,'Setup - Mix Design'!$A$5:$I$504,7,0)),"")
F15: =IFERROR(IF(OR(C15="",D15=""),"",D15*VLOOKUP(C15,'Setup - Mix Design'!$A$5:$I$504,2,0)),"") | G15: =IFERROR(IF(OR(C15="",D15=""),"",D15*VLOOKUP(C15,'Setup - Mix Design'!$A$5:$I$504,3,0)),"") | H15: =IFERROR(IF(OR(C15="",D15=""),"",D15*VLOOKUP(C15,'Setup - Mix Design'!$A$5:$I$504,4,0)),"") | I15: =IFERROR(IF(OR(C15="",D15=""),"",D15*VLOOKUP(C15,'Setup - Mix Design'!$A$5:$I$504,5,0)),"") | J15: =IFERROR(IF(OR(C15="",D15=""),"",D15*VLOOKUP(C15,'Setup - Mix Design'!$A$5:$I$504,6,0)),"") | K15: =IFERROR(IF(OR(C15="",D15=""),"",D15*VLOOKUP(C15,'Setup - Mix Design'!$A$5:$I$504,7,0)),"")
F16: =IFERROR(IF(OR(C16="",D16=""),"",D16*VLOOKUP(C16,'Setup - Mix Design'!$A$5:$I$504,2,0)),"") | G16: =IFERROR(IF(OR(C16="",D16=""),"",D16*VLOOKUP(C16,'Setup - Mix Design'!$A$5:$I$504,3,0)),"") | H16: =IFERROR(IF(OR(C16="",D16=""),"",D16*VLOOKUP(C16,'Setup - Mix Design'!$A$5:$I$504,4,0)),"") | I16: =IFERROR(IF(OR(C16="",D16=""),"",D16*VLOOKUP(C16,'Setup - Mix Design'!$A$5:$I$504,5,0)),"") | J16: =IFERROR(IF(OR(C16="",D16=""),"",D16*VLOOKUP(C16,'Setup - Mix Design'!$A$5:$I$504,6,0)),"") | K16: =IFERROR(IF(OR(C16="",D16=""),"",D16*VLOOKUP(C16,'Setup - Mix Design'!$A$5:$I$504,7,0)),"")
... F6004: =IFERROR(IF(OR(C6004="",D6004=""),"",D6004*VLOOKUP(C6004,'Setup - Mix Design'!$A$5:$I$504,2,0)),"") | G6004: =IFERROR(IF(OR(C6004="",D6004=""),"",D6004*VLOOKUP(C6004,'Setup - Mix Design'!$A$5:$I$504,3,0)),"") | H6004: =IFERROR(IF(OR(C6004="",D6004=""),"",D6004*VLOOKUP(C6004,'Setup - Mix Design'!$A$5:$I$504,4,0)),"") | I6004: =IFERROR(IF(OR(C6004="",D6004=""),"",D6004*VLOOKUP(C6004,'Setup - Mix Design'!$A$5:$I$504,5,0)),"") | J6004: =IFERROR(IF(OR(C6004="",D6004=""),"",D6004*VLOOKUP(C6004,'Setup - Mix Design'!$A$5:$I$504,6,0)),"") | K6004: =IFERROR(IF(OR(C6004="",D6004=""),"",D6004*VLOOKUP(C6004,'Setup - Mix Design'!$A$5:$I$504,7,0)),"")

Sheet Batch Report
A1: CONCRETE KING
A2: BATCH REPORT • Target Mix per Batch
B4: Select Grade: | D4: Production Qty (m³):
B6: Plant | C6: ="CONCRETE KING" | D6: Recipe / Grade | E6: =IF($C$4="","",$C$4)
B7: Batch No | D7: Batch Date
B8: Truck No | D8: W/C Ratio | E8: =IFERROR(IF($C$4="","",VLOOKUP($C$4,'Setup - Mix Design'!$A$5:$I$504,8,0)),"")
B9: Customer | D9: Production Qty (m³) | E9: =IF($E$4="","",$E$4)
B11: Material | C11: Per m³ | D11: Total (× Qty) | E11: Unit
B12: Cement | C12: =IFERROR(IF($C$4="","",VLOOKUP($C$4,'Setup - Mix Design'!$A$5:$I$504,2,0)),"") | D12: =IF(OR($C$4="",$E$4="",C12=""),"",C12*$E$4) | E12: kg
B13: Sand | C13: =IFERROR(IF($C$4="","",VLOOKUP($C$4,'Setup - Mix Design'!$A$5:$I$504,3,0)),"") | D13: =IF(OR($C$4="",$E$4="",C13=""),"",C13*$E$4) | E13: kg
B14: Aggregate 20mm | C14: =IFERROR(IF($C$4="","",VLOOKUP($C$4,'Setup - Mix Design'!$A$5:$I$504,4,0)),"") | D14: =IF(OR($C$4="",$E$4="",C14=""),"",C14*$E$4) | E14: kg
B15: Aggregate 10mm | C15: =IFERROR(IF($C$4="","",VLOOKUP($C$4,'Setup - Mix Design'!$A$5:$I$504,5,0)),"") | D15: =IF(OR($C$4="",$E$4="",C15=""),"",C15*$E$4) | E15: kg
B16: Water | C16: =IFERROR(IF($C$4="","",VLOOKUP($C$4,'Setup - Mix Design'!$A$5:$I$504,6,0)),"") | D16: =IF(OR($C$4="",$E$4="",C16=""),"",C16*$E$4) | E16: ltr
B17: Admixture | C17: =IFERROR(IF($C$4="","",VLOOKUP($C$4,'Setup - Mix Design'!$A$5:$I$504,7,0)),"") | D17: =IF(OR($C$4="",$E$4="",C17=""),"",C17*$E$4) | E17: kg
B18: TOTAL MASS | D18: =IF($C$4="","",SUM(D12:D17)) | E18: kg
B20: =HYPERLINK("https://wa.me/?text="&SUBSTITUTE("*CONCRETE KING - Batch Report*%0AGrade: "&$C$4&"%0AQty: "&$E$4&" m3%0ABatch No: "&$C$7&"%0ADate: "&TEXT($E$7,"dd-mmm-yyyy")&"%0ACement: "&D12&" kg%0ASand: "&D13&" kg"&"%0AAgg20: "&D14&" kg%0AAgg10: "&D15&" kg%0AWater: "&D16&" L%0AAdmix: "&D17&" kg%0ATotal: "&D18&" kg"," ","%20"),"📲 Send Batch Report on WhatsApp") | D20: 🖨 Press Ctrl+P (phone: Share ▸ Print) to Print / Save as PDF

Sheet Material Receipt
A1: Material Receipt - Purchases
A2: Incoming raw material. Unit auto-fills; amount auto-calculates. Feeds 'Received' in Stock.
A4: Date | B4: Material | C4: Qty Received | D4: Unit | E4: Rate (₹/unit) | F4: Amount (₹) | G4: Supplier | H4: Invoice No.
D5: =IFERROR(IF(B5="","",VLOOKUP(B5,'Setup - Materials'!$A$5:$E$504,2,0)),"") | F5: =IF(OR(C5="",E5=""),"",C5*E5)
D6: =IFERROR(IF(B6="","",VLOOKUP(B6,'Setup - Materials'!$A$5:$E$504,2,0)),"") | F6: =IF(OR(C6="",E6=""),"",C6*E6)
D7: =IFERROR(IF(B7="","",VLOOKUP(B7,'Setup - Materials'!$A$5:$E$504,2,0)),"") | F7: =IF(OR(C7="",E7=""),"",C7*E7)
D8: =IFERROR(IF(B8="","",VLOOKUP(B8,'Setup - Materials'!$A$5:$E$504,2,0)),"") | F8: =IF(OR(C8="",E8=""),"",C8*E8)
D9: =IFERROR(IF(B9="","",VLOOKUP(B9,'Setup - Materials'!$A$5:$E$504,2,0)),"") | F9: =IF(OR(C9="",E9=""),"",C9*E9)
D10: =IFERROR(IF(B10="","",VLOOKUP(B10,'Setup - Materials'!$A$5:$E$504,2,0)),"") | F10: =IF(OR(C10="",E10=""),"",C10*E10)
D11: =IFERROR(IF(B11="","",VLOOKUP(B11,'Setup - Materials'!$A$5:$E$504,2,0)),"") | F11: =IF(OR(C11="",E11=""),"",C11*E11)
D12: =IFERROR(IF(B12="","",VLOOKUP(B12,'Setup - Materials'!$A$5:$E$504,2,0)),"") | F12: =IF(OR(C12="",E12=""),"",C12*E12)
D13: =IFERROR(IF(B13="","",VLOOKUP(B13,'Setup - Materials'!$A$5:$E$504,2,0)),"") | F13: =IF(OR(C13="",E13=""),"",C13*E13)
D14: =IFERROR(IF(B14="","",VLOOKUP(B14,'Setup - Materials'!$A$5:$E$504,2,0)),"") | F14: =IF(OR(C14="",E14=""),"",C14*E14)
D15: =IFERROR(IF(B15="","",VLOOKUP(B15,'Setup - Materials'!$A$5:$E$504,2,0)),"") | F15: =IF(OR(C15="",E15=""),"",C15*E15)
D16: =IFERROR(IF(B16="","",VLOOKUP(B16,'Setup - Materials'!$A$5:$E$504,2,0)),"") | F16: =IF(OR(C16="",E16=""),"",C16*E16)
... D6004: =IFERROR(IF(B6004="","",VLOOKUP(B6004,'Setup - Materials'!$A$5:$E$504,2,0)),"") | F6004: =IF(OR(C6004="",E6004=""),"",C6004*E6004)

Sheet Fuel Log
A1: Fuel Log - Diesel Issued
A2: Diesel issued per vehicle. Amount auto-calculates; total diesel feeds Stock.
A4: Date | B4: Vehicle No. | C4: Diesel (ltr) | D4: Odometer (km) | E4: Rate (₹/ltr) | F4: Amount (₹) | G4: Filled By
F5: =IF(OR(C5="",E5=""),"",C5*E5)
F6: =IF(OR(C6="",E6=""),"",C6*E6)
F7: =IF(OR(C7="",E7=""),"",C7*E7)
F8: =IF(OR(C8="",E8=""),"",C8*E8)
F9: =IF(OR(C9="",E9=""),"",C9*E9)
F10: =IF(OR(C10="",E10=""),"",C10*E10)
F11: =IF(OR(C11="",E11=""),"",C11*E11)
F12: =IF(OR(C12="",E12=""),"",C12*E12)
F13: =IF(OR(C13="",E13=""),"",C13*E13)
F14: =IF(OR(C14="",E14=""),"",C14*E14)
F15: =IF(OR(C15="",E15=""),"",C15*E15)
F16: =IF(OR(C16="",E16=""),"",C16*E16)
... F6004: =IF(OR(C6004="",E6004=""),"",C6004*E6004)

Sheet Payments
A1: Payments - Customer Collections
A2: Money received from clients. Drives 'Collection' and 'Outstanding' on the Dashboard.
A4: Date | B4: Receipt No. | C4: Client | D4: Amount Received (₹) | E4: Mode | F4: Reference / Notes

Sheet Cube Test Register
A1: Cube Test Register - Quality Control
A2: Strength = Load(kN)x1000 / 22500mm2 (150mm cube). Pass/Fail auto-checks vs the grade's required N/mm2.
A4: Casting Date | B4: Cube ID | C4: Challan / Ref | D4: Grade | E4: Testing Date | F4: Age (days) | G4: Load (kN) | H4: Strength (N/mm2) | I4: Required (N/mm2) | J4: Result
F5: =IF(OR(A5="",E5=""),"",E5-A5) | H5: =IF(G5="","",ROUND(G5*1000/22500,2)) | I5: =IFERROR(IF(D5="","",VALUE(MID(D5,2,5))),"") | J5: =IF(OR(H5="",I5=""),"",IF(H5>=I5,"Pass","Fail"))
F6: =IF(OR(A6="",E6=""),"",E6-A6) | H6: =IF(G6="","",ROUND(G6*1000/22500,2)) | I6: =IFERROR(IF(D6="","",VALUE(MID(D6,2,5))),"") | J6: =IF(OR(H6="",I6=""),"",IF(H6>=I6,"Pass","Fail"))
F7: =IF(OR(A7="",E7=""),"",E7-A7) | H7: =IF(G7="","",ROUND(G7*1000/22500,2)) | I7: =IFERROR(IF(D7="","",VALUE(MID(D7,2,5))),"") | J7: =IF(OR(H7="",I7=""),"",IF(H7>=I7,"Pass","Fail"))
F8: =IF(OR(A8="",E8=""),"",E8-A8) | H8: =IF(G8="","",ROUND(G8*1000/22500,2)) | I8: =IFERROR(IF(D8="","",VALUE(MID(D8,2,5))),"") | J8: =IF(OR(H8="",I8=""),"",IF(H8>=I8,"Pass","Fail"))
F9: =IF(OR(A9="",E9=""),"",E9-A9) | H9: =IF(G9="","",ROUND(G9*1000/22500,2)) | I9: =IFERROR(IF(D9="","",VALUE(MID(D9,2,5))),"") | J9: =IF(OR(H9="",I9=""),"",IF(H9>=I9,"Pass","Fail"))
F10: =IF(OR(A10="",E10=""),"",E10-A10) | H10: =IF(G10="","",ROUND(G10*1000/22500,2)) | I10: =IFERROR(IF(D10="","",VALUE(MID(D10,2,5))),"") | J10: =IF(OR(H10="",I10=""),"",IF(H10>=I10,"Pass","Fail"))
F11: =IF(OR(A11="",E11=""),"",E11-A11) | H11: =IF(G11="","",ROUND(G11*1000/22500,2)) | I11: =IFERROR(IF(D11="","",VALUE(MID(D11,2,5))),"") | J11: =IF(OR(H11="",I11=""),"",IF(H11>=I11,"Pass","Fail"))
F12: =IF(OR(A12="",E12=""),"",E12-A12) | H12: =IF(G12="","",ROUND(G12*1000/22500,2)) | I12: =IFERROR(IF(D12="","",VALUE(MID(D12,2,5))),"") | J12: =IF(OR(H12="",I12=""),"",IF(H12>=I12,"Pass","Fail"))
F13: =IF(OR(A13="",E13=""),"",E13-A13) | H13: =IF(G13="","",ROUND(G13*1000/22500,2)) | I13: =IFERROR(IF(D13="","",VALUE(MID(D13,2,5))),"") | J13: =IF(OR(H13="",I13=""),"",IF(H13>=I13,"Pass","Fail"))
F14: =IF(OR(A14="",E14=""),"",E14-A14) | H14: =IF(G14="","",ROUND(G14*1000/22500,2)) | I14: =IFERROR(IF(D14="","",VALUE(MID(D14,2,5))),"") | J14: =IF(OR(H14="",I14=""),"",IF(H14>=I14,"Pass","Fail"))
F15: =IF(OR(A15="",E15=""),"",E15-A15) | H15: =IF(G15="","",ROUND(G15*1000/22500,2)) | I15: =IFERROR(IF(D15="","",VALUE(MID(D15,2,5))),"") | J15: =IF(OR(H15="",I15=""),"",IF(H15>=I15,"Pass","Fail"))
F16: =IF(OR(A16="",E16=""),"",E16-A16) | H16: =IF(G16="","",ROUND(G16*1000/22500,2)) | I16: =IFERROR(IF(D16="","",VALUE(MID(D16,2,5))),"") | J16: =IF(OR(H16="",I16=""),"",IF(H16>=I16,"Pass","Fail"))
... F6004: =IF(OR(A6004="",E6004=""),"",E6004-A6004) | H6004: =IF(G6004="","",ROUND(G6004*1000/22500,2)) | I6004: =IFERROR(IF(D6004="","",VALUE(MID(D6004,2,5))),"") | J6004: =IF(OR(H6004="",I6004=""),"",IF(H6004>=I6004,"Pass","Fail"))

Sheet Stock Register
A1: Stock Register - Live Balances
A2: Opening + Received - Consumed = Closing. Closing turns RED when it drops below the reorder level.
A4: Material | B4: Unit | C4: Opening | D4: Received | E4: Consumed | F4: Closing Stock | G4: Reorder Level | H4: Value (₹)
A5: Cement | B5: =IFERROR(VLOOKUP(A5,'Setup - Materials'!$A$5:$E$504,2,0),"") | C5: =IFERROR(VLOOKUP(A5,'Setup - Materials'!$A$5:$E$504,3,0),0) | D5: =SUMIF('Material Receipt'!$B$5:$B$6004,A5,'Material Receipt'!$C$5:$C$6004) | E5: =SUM('Batch Production'!$F$5:$F$6004) | F5: =C5+D5-E5 | G5: =IFERROR(VLOOKUP(A5,'Setup - Materials'!$A$5:$E$504,5,0),0) | H5: =IFERROR(F5*VLOOKUP(A5,'Setup - Materials'!$A$5:$E$504,4,0),"")
A6: Sand | B6: =IFERROR(VLOOKUP(A6,'Setup - Materials'!$A$5:$E$504,2,0),"") | C6: =IFERROR(VLOOKUP(A6,'Setup - Materials'!$A$5:$E$504,3,0),0) | D6: =SUMIF('Material Receipt'!$B$5:$B$6004,A6,'Material Receipt'!$C$5:$C$6004) | E6: =SUM('Batch Production'!$G$5:$G$6004) | F6: =C6+D6-E6 | G6: =IFERROR(VLOOKUP(A6,'Setup - Materials'!$A$5:$E$504,5,0),0) | H6: =IFERROR(F6*VLOOKUP(A6,'Setup - Materials'!$A$5:$E$504,4,0),"")
A7: Aggregate 20mm | B7: =IFERROR(VLOOKUP(A7,'Setup - Materials'!$A$5:$E$504,2,0),"") | C7: =IFERROR(VLOOKUP(A7,'Setup - Materials'!$A$5:$E$504,3,0),0) | D7: =SUMIF('Material Receipt'!$B$5:$B$6004,A7,'Material Receipt'!$C$5:$C$6004) | E7: =SUM('Batch Production'!$H$5:$H$6004) | F7: =C7+D7-E7 | G7: =IFERROR(VLOOKUP(A7,'Setup - Materials'!$A$5:$E$504,5,0),0) | H7: =IFERROR(F7*VLOOKUP(A7,'Setup - Materials'!$A$5:$E$504,4,0),"")
A8: Aggregate 10mm | B8: =IFERROR(VLOOKUP(A8,'Setup - Materials'!$A$5:$E$504,2,0),"") | C8: =IFERROR(VLOOKUP(A8,'Setup - Materials'!$A$5:$E$504,3,0),0) | D8: =SUMIF('Material Receipt'!$B$5:$B$6004,A8,'Material Receipt'!$C$5:$C$6004) | E8: =SUM('Batch Production'!$I$5:$I$6004) | F8: =C8+D8-E8 | G8: =IFERROR(VLOOKUP(A8,'Setup - Materials'!$A$5:$E$504,5,0),0) | H8: =IFERROR(F8*VLOOKUP(A8,'Setup - Materials'!$A$5:$E$504,4,0),"")
A9: Admixture | B9: =IFERROR(VLOOKUP(A9,'Setup - Materials'!$A$5:$E$504,2,0),"") | C9: =IFERROR(VLOOKUP(A9,'Setup - Materials'!$A$5:$E$504,3,0),0) | D9: =SUMIF('Material Receipt'!$B$5:$B$6004,A9,'Material Receipt'!$C$5:$C$6004) | E9: =SUM('Batch Production'!$K$5:$K$6004) | F9: =C9+D9-E9 | G9: =IFERROR(VLOOKUP(A9,'Setup - Materials'!$A$5:$E$504,5,0),0) | H9: =IFERROR(F9*VLOOKUP(A9,'Setup - Materials'!$A$5:$E$504,4,0),"")
A10: Diesel | B10: =IFERROR(VLOOKUP(A10,'Setup - Materials'!$A$5:$E$504,2,0),"") | C10: =IFERROR(VLOOKUP(A10,'Setup - Materials'!$A$5:$E$504,3,0),0) | D10: =SUMIF('Material Receipt'!$B$5:$B$6004,A10,'Material Receipt'!$C$5:$C$6004) | E10: =SUM('Fuel Log'!$C$5:$C$6004) | F10: =C10+D10-E10 | G10: =IFERROR(VLOOKUP(A10,'Setup - Materials'!$A$5:$E$504,5,0),0) | H10: =IFERROR(F10*VLOOKUP(A10,'Setup - Materials'!$A$5:$E$504,4,0),"")
A11: TOTAL | H11: =SUM(H5:H10)

Sheet Lists
A1: Vehicle Status | B1: Dispatch Status | C1: Payment Mode
A2: Active | B2: Scheduled | C2: Cash
A3: Maintenance | B3: Dispatched | C3: UPI
A4: Inactive | B4: Delivered | C4: Cheque
B5: Cancelled | C5: NEFT
C6: RTGS
